{
  "key": "35UK579T",
  "version": 6201,
  "library": {
    "type": "group",
    "id": 4394244,
    "name": "TibSchol",
    "links": {
      "alternate": {
        "href": "https://www.zotero.org/groups/tibschol",
        "type": "text/html"
      }
    }
  },
  "links": {
    "self": {
      "href": "https://api.zotero.org/groups/4394244/items/35UK579T",
      "type": "application/json"
    },
    "alternate": {
      "href": "https://www.zotero.org/groups/tibschol/items/35UK579T",
      "type": "text/html"
    }
  },
  "meta": {
    "createdByUser": {
      "id": 8397006,
      "username": "PascaleHugon",
      "name": "",
      "links": {
        "alternate": {
          "href": "https://www.zotero.org/pascalehugon",
          "type": "text/html"
        }
      }
    },
    "creatorSummary": "Funayama",
    "parsedDate": "2001",
    "numChildren": 0
  },
  "data": {
    "key": "35UK579T",
    "version": 6201,
    "itemType": "bookSection",
    "title": "On the Date of Vinitadeva",
    "creators": [
      {
        "creatorType": "author",
        "firstName": "Toru",
        "lastName": "Funayama"
      },
      {
        "creatorType": "editor",
        "firstName": "Raffaele",
        "lastName": "Torella"
      }
    ],
    "abstractNote": "",
    "bookTitle": "Le Parole e i Marmi",
    "series": "",
    "seriesNumber": "",
    "volume": "",
    "numberOfVolumes": "",
    "edition": "",
    "date": "2001",
    "publisher": "",
    "place": "",
    "originalDate": "",
    "originalPublisher": "",
    "originalPlace": "",
    "format": "",
    "pages": "309\u2013325",
    "ISBN": "",
    "DOI": "",
    "citationKey": "",
    "url": "",
    "accessDate": "",
    "ISSN": "",
    "archive": "",
    "archiveLocation": "",
    "shortTitle": "Funayama 2001",
    "language": "",
    "libraryCatalog": "",
    "callNumber": "",
    "rights": "",
    "extra": "Version Number: 2010-03-19 02:15:58\n_eprint: 3235",
    "tags": [
      {
        "tag": "APIS"
      }
    ],
    "collections": [],
    "relations": {},
    "dateAdded": "2026-03-10T14:40:25Z",
    "dateModified": "2026-03-10T14:40:43Z"
  }
}