{
  "key": "CTSKHPIC",
  "version": 4697,
  "library": {
    "type": "group",
    "id": 4394244,
    "name": "TibSchol",
    "links": {
      "alternate": {
        "href": "https://www.zotero.org/groups/tibschol",
        "type": "text/html"
      }
    }
  },
  "links": {
    "self": {
      "href": "https://api.zotero.org/groups/4394244/items/CTSKHPIC",
      "type": "application/json"
    },
    "alternate": {
      "href": "https://www.zotero.org/groups/tibschol/items/CTSKHPIC",
      "type": "text/html"
    }
  },
  "meta": {
    "createdByUser": {
      "id": 8397006,
      "username": "PascaleHugon",
      "name": "",
      "links": {
        "alternate": {
          "href": "https://www.zotero.org/pascalehugon",
          "type": "text/html"
        }
      }
    },
    "creatorSummary": "Kano",
    "parsedDate": "2009",
    "numChildren": 1
  },
  "data": {
    "key": "CTSKHPIC",
    "version": 4697,
    "itemType": "journalArticle",
    "title": "\u52a0\u7d0d\u548c\u96c4, \u30b4\u30af\u30fb\u30ed\u30c7\u30f3\u30b7\u30a7\u30fc\u30e9\u30d7\u8457\u300e\u66f8\u7c21\u30fb\u7518\u9732\u306e\u6ef4\u300f\u2015\u8a33\u6ce8\u7bc7\u2015 [rNgog Blo ldan shes rab's <i>sPring yig bdud rtsi'i thigs pa</i> \u2013 Annotated Japanese translation]",
    "creators": [
      {
        "creatorType": "author",
        "firstName": "Kazuo (\u52a0\u7d0d\u548c\u96c4)",
        "lastName": "Kano"
      }
    ],
    "abstractNote": "",
    "publicationTitle": "\u5bc6\u6559\u6587\u5316\u7814\u7a76\u6240\u7d00\u8981 (Mikky\u014dbunka kenky\u016bjo kiy\u014d)",
    "volume": "22",
    "issue": "",
    "pages": "121\u2013178",
    "date": "2009",
    "series": "",
    "seriesTitle": "",
    "seriesText": "",
    "journalAbbreviation": "",
    "language": "jap, tib",
    "DOI": "",
    "ISSN": "",
    "shortTitle": "Kano 2009",
    "url": "https://www.koyasan-u.ac.jp/laboratory/pdf/kiyo22/22_kanoh.pdf",
    "accessDate": "",
    "archive": "",
    "archiveLocation": "",
    "libraryCatalog": "",
    "callNumber": "",
    "rights": "",
    "extra": "With a commented list of the works in KDSB Set 2",
    "tags": [
      {
        "tag": "APIS"
      },
      {
        "tag": "Gateway"
      },
      {
        "tag": "rNgog Blo ldan shes rab"
      }
    ],
    "collections": [],
    "relations": {
      "owl:sameAs": "http://zotero.org/groups/4973569/items/5UZNUN24"
    },
    "dateAdded": "2024-09-20T13:31:41Z",
    "dateModified": "2025-05-21T07:07:25Z"
  }
}