{
  "key": "EFRFGQZI",
  "version": 4959,
  "library": {
    "type": "group",
    "id": 4394244,
    "name": "TibSchol",
    "links": {
      "alternate": {
        "href": "https://www.zotero.org/groups/tibschol",
        "type": "text/html"
      }
    }
  },
  "links": {
    "self": {
      "href": "https://api.zotero.org/groups/4394244/items/EFRFGQZI",
      "type": "application/json"
    },
    "alternate": {
      "href": "https://www.zotero.org/groups/tibschol/items/EFRFGQZI",
      "type": "text/html"
    }
  },
  "meta": {
    "createdByUser": {
      "id": 8397006,
      "username": "PascaleHugon",
      "name": "",
      "links": {
        "alternate": {
          "href": "https://www.zotero.org/pascalehugon",
          "type": "text/html"
        }
      }
    },
    "creatorSummary": "rNgog Blo ldan shes rab",
    "parsedDate": "2018",
    "numChildren": 0
  },
  "data": {
    "key": "EFRFGQZI",
    "version": 4959,
    "itemType": "bookSection",
    "title": "shes rab snying po'i rgya cher 'grel gyi bshad pa",
    "creators": [
      {
        "creatorType": "editor",
        "firstName": "",
        "lastName": "sMon bzang dpe rnying 'tshol bsdu khang"
      },
      {
        "creatorType": "author",
        "firstName": "",
        "lastName": "rNgog Blo ldan shes rab"
      }
    ],
    "abstractNote": "",
    "bookTitle": "sTong ra mkhan brgyud kyi gsung 'bum",
    "series": "",
    "seriesNumber": "",
    "volume": "1",
    "numberOfVolumes": "3",
    "edition": "",
    "date": "2018",
    "publisher": "Bod ljongs bod yig dpe rnying dpe skrung khang",
    "place": "Lhasa",
    "originalDate": "",
    "originalPublisher": "",
    "originalPlace": "",
    "format": "",
    "pages": "425-436",
    "ISBN": "",
    "DOI": "",
    "citationKey": "",
    "url": "",
    "accessDate": "",
    "ISSN": "",
    "archive": "",
    "archiveLocation": "BDRC No: MW3CN21546",
    "shortTitle": "rNgog lo - shes rab snying po don bsdus 2018 ed",
    "language": "tib",
    "libraryCatalog": "",
    "callNumber": "",
    "rights": "",
    "extra": "",
    "tags": [
      {
        "tag": "APIS"
      },
      {
        "tag": "Gateway"
      }
    ],
    "collections": [
      "IEP4UFSV"
    ],
    "relations": {
      "dc:relation": "http://zotero.org/groups/4394244/items/8WSB3UGM"
    },
    "dateAdded": "2024-01-15T14:32:42Z",
    "dateModified": "2025-04-24T09:03:10Z"
  }
}