{
  "key": "ITEYGN38",
  "version": 5811,
  "library": {
    "type": "group",
    "id": 4394244,
    "name": "TibSchol",
    "links": {
      "alternate": {
        "href": "https://www.zotero.org/groups/tibschol",
        "type": "text/html"
      }
    }
  },
  "links": {
    "self": {
      "href": "https://api.zotero.org/groups/4394244/items/ITEYGN38",
      "type": "application/json"
    },
    "alternate": {
      "href": "https://www.zotero.org/groups/tibschol/items/ITEYGN38",
      "type": "text/html"
    }
  },
  "meta": {
    "createdByUser": {
      "id": 8397006,
      "username": "PascaleHugon",
      "name": "",
      "links": {
        "alternate": {
          "href": "https://www.zotero.org/pascalehugon",
          "type": "text/html"
        }
      }
    },
    "creatorSummary": "Pa tshab Nyi ma grags",
    "numChildren": 0
  },
  "data": {
    "key": "ITEYGN38",
    "version": 5811,
    "itemType": "bookSection",
    "title": "dbu ma rtsa ba shes rab kyi spyi sdom",
    "creators": [
      {
        "creatorType": "bookAuthor",
        "firstName": "",
        "lastName": "Pa tshab Nyi ma grags"
      },
      {
        "creatorType": "author",
        "firstName": "",
        "lastName": "Pa tshab Nyi ma grags"
      }
    ],
    "abstractNote": "",
    "bookTitle": "rTsa shes kyi \u1e6d\u012b ka dang tshig gsal gyi dka\u02bc gnad spyi sdom bcas",
    "series": "",
    "seriesNumber": "",
    "volume": "",
    "numberOfVolumes": "1",
    "edition": "",
    "place": "gser rta rdzong",
    "publisher": "gser ljongs bla rung lnga rig nang bstan slob grwa chen mo",
    "date": "",
    "pages": "389-397",
    "language": "tib",
    "ISBN": "",
    "shortTitle": "Pa tshab - dbu rtsa shes rab spyi sdom ed.",
    "url": "http://purl.bdrc.io/resource/MW3CN3438",
    "accessDate": "",
    "archive": "",
    "archiveLocation": "",
    "libraryCatalog": "",
    "callNumber": "",
    "rights": "",
    "extra": "",
    "tags": [
      {
        "tag": "APIS"
      },
      {
        "tag": "Madhyamaka"
      }
    ],
    "collections": [],
    "relations": {
      "dc:relation": "http://zotero.org/groups/4394244/items/7MEK37AB"
    },
    "dateAdded": "2025-11-25T18:24:10Z",
    "dateModified": "2025-11-25T18:29:47Z"
  }
}