{
  "key": "ZH39FJT7",
  "version": 4953,
  "library": {
    "type": "group",
    "id": 4394244,
    "name": "TibSchol",
    "links": {
      "alternate": {
        "href": "https://www.zotero.org/groups/tibschol",
        "type": "text/html"
      }
    }
  },
  "links": {
    "self": {
      "href": "https://api.zotero.org/groups/4394244/items/ZH39FJT7",
      "type": "application/json"
    },
    "alternate": {
      "href": "https://www.zotero.org/groups/tibschol/items/ZH39FJT7",
      "type": "text/html"
    }
  },
  "meta": {
    "createdByUser": {
      "id": 8397006,
      "username": "PascaleHugon",
      "name": "",
      "links": {
        "alternate": {
          "href": "https://www.zotero.org/pascalehugon",
          "type": "text/html"
        }
      }
    },
    "creatorSummary": "van der Kuijp",
    "parsedDate": "2020",
    "numChildren": 0
  },
  "data": {
    "key": "ZH39FJT7",
    "version": 4953,
    "itemType": "journalArticle",
    "title": "Indo-Tibetan Tantric Buddhist Scholasticism: Bhavyak\u012brti and His Summary of S\u0101\u1e41khya Philosophy (Part I)",
    "creators": [
      {
        "creatorType": "author",
        "firstName": "Leonard W.J.",
        "lastName": "van der Kuijp"
      }
    ],
    "abstractNote": "",
    "publicationTitle": "Journal of Tibetan and Himalayan Studies",
    "volume": "5",
    "issue": "1",
    "pages": "1-40",
    "date": "2020",
    "series": "",
    "seriesTitle": "",
    "seriesText": "",
    "journalAbbreviation": "",
    "language": "eng",
    "DOI": "",
    "ISSN": "",
    "shortTitle": "van der Kuijp 2020",
    "url": "",
    "accessDate": "",
    "archive": "",
    "archiveLocation": "",
    "libraryCatalog": "",
    "callNumber": "",
    "rights": "",
    "extra": "",
    "tags": [
      {
        "tag": "Scholasticism"
      },
      {
        "tag": "Tantric Buddhism"
      }
    ],
    "collections": [
      "YVHDSL7M"
    ],
    "relations": {},
    "dateAdded": "2025-03-13T08:45:41Z",
    "dateModified": "2025-05-21T08:19:35Z"
  }
}